segmentationmetrics/__init__.py
segmentationmetrics/metrics.py
segmentationmetrics/surface_distance/__init__.py
segmentationmetrics/surface_distance/lookup_tables.py
segmentationmetrics/surface_distance/metrics.py
segmentationmetrics/tests/__init__.py
segmentationmetrics/tests/test_metrics.py
segmentationmetrics/tests/test_surface_distance.py
segmentationmetrics-1.1.2.dist-info/licenses/LICENSE.md
segmentationmetrics-1.1.2.dist-info/METADATA
segmentationmetrics-1.1.2.dist-info/WHEEL
segmentationmetrics-1.1.2.dist-info/top_level.txt
segmentationmetrics-1.1.2.dist-info/RECORD
