Metadata-Version: 2.4
Name: segmentationmetrics
Version: 1.1.2
Summary: Binary segmentation accuracy metrics
Home-page: https://github.com/alexdaniel654/Segmentation_Metrics
License: Apache-2.0
Classifier: Development Status :: 5 - Production/Stable
Classifier: Intended Audience :: Developers
Classifier: Intended Audience :: Science/Research
Classifier: Topic :: Scientific/Engineering
Classifier: Environment :: Console
Classifier: Operating System :: OS Independent
Classifier: Programming Language :: Python :: 3.9
Classifier: Programming Language :: Python :: 3.10
Classifier: Programming Language :: Python :: 3.11
Classifier: Programming Language :: Python :: 3.12
Classifier: Programming Language :: Python :: 3.13
Classifier: License :: OSI Approved :: Apache Software License
Requires-Python: >=3.9, <4
License-File: LICENSE.md
Requires-Dist: absl-py>=2.1.0
Requires-Dist: numpy>=2.0.1
Requires-Dist: pandas>=2.2.3
Requires-Dist: pytest>=8.3.2
Requires-Dist: scikit-image>=0.24.0
Requires-Dist: scipy>=1.13.1
Dynamic: classifier
Dynamic: description
Dynamic: description-content-type
Dynamic: home-page
Dynamic: license
Dynamic: license-file
Dynamic: requires-dist
Dynamic: requires-python
Dynamic: summary
